{
  "news": [
    {
      "id": 1,
      "title": "قمة نارية بين أرسنال وتشيلسي",
      "cover": "https://picsum.photos/900/500?news1",
      "content": "مباراة قوية منتظرة اليوم بين أرسنال وتشيلسي ضمن الدوري الإنجليزي الممتاز.",
      "timeAgo": "1 hour ago"
    },
    {
      "id": 2,
      "title": "برشلونة يواجه ريال مدريد في الكلاسيكو",
      "cover": "https://picsum.photos/900/500?news2",
      "content": "مواجهة قوية بين برشلونة وريال مدريد في كلاسيكو ناري.",
      "timeAgo": "2 hours ago"
    },
    {
      "id": 3,
      "title": "بايرن ميونخ في مواجهة صعبة",
      "cover": "https://picsum.photos/900/500?news3",
      "content": "بايرن ميونخ يستعد لمواجهة قوية في دوري الأبطال.",
      "timeAgo": "3 hours ago"
    }
  ],

  "leagues": [
    {
      "id": 1,
      "name": "Premier League",
      "image": "https://picsum.photos/300/300?league1"
    },
    {
      "id": 2,
      "name": "La Liga",
      "image": "https://picsum.photos/300/300?league2"
    },
    {
      "id": 3,
      "name": "Champions League",
      "image": "https://picsum.photos/300/300?league3"
    },
    {
      "id": 4,
      "name": "Serie A",
      "image": "https://picsum.photos/300/300?league4"
    }
  ],

  "matches": [
    {
      "id": 1,
      "leagueId": 1,
      "leagueName": "Premier League",
      "homeTeam": "Arsenal",
      "awayTeam": "Chelsea",
      "homeLogo": "https://upload.wikimedia.org/wikipedia/en/5/53/Arsenal_FC.svg",
      "awayLogo": "https://upload.wikimedia.org/wikipedia/en/c/cc/Chelsea_FC.svg",
      "time": "03:45 PM",
      "thumbnail": "https://picsum.photos/900/500?match1",
      "isLive": true,
      "streamTitle": "Arsenal vs Chelsea",
      "streamUrl": "https://test-streams.mux.dev/x36xhzz/x36xhzz.m3u8"
    },
    {
      "id": 2,
      "leagueId": 1,
      "leagueName": "Premier League",
      "homeTeam": "Liverpool",
      "awayTeam": "Manchester City",
      "homeLogo": "https://upload.wikimedia.org/wikipedia/en/0/0c/Liverpool_FC.svg",
      "awayLogo": "https://upload.wikimedia.org/wikipedia/en/e/eb/Manchester_City_FC_badge.svg",
      "time": "07:00 PM",
      "thumbnail": "https://picsum.photos/900/500?match2",
      "isLive": false,
      "streamTitle": "Liverpool vs Man City",
      "streamUrl": "https://www.w3schools.com/html/mov_bbb.mp4"
    },
    {
      "id": 3,
      "leagueId": 2,
      "leagueName": "La Liga",
      "homeTeam": "Barcelona",
      "awayTeam": "Real Madrid",
      "homeLogo": "https://upload.wikimedia.org/wikipedia/en/4/47/FC_Barcelona_%28crest%29.svg",
      "awayLogo": "https://upload.wikimedia.org/wikipedia/en/5/56/Real_Madrid_CF.svg",
      "time": "08:00 PM",
      "thumbnail": "https://picsum.photos/900/500?match3",
      "isLive": true,
      "streamTitle": "Barcelona vs Real Madrid",
      "streamUrl": "https://test-streams.mux.dev/x36xhzz/x36xhzz.m3u8"
    },
    {
      "id": 4,
      "leagueId": 3,
      "leagueName": "Champions League",
      "homeTeam": "PSG",
      "awayTeam": "Bayern Munich",
      "homeLogo": "https://upload.wikimedia.org/wikipedia/en/a/a7/Paris_Saint-Germain_F.C..svg",
      "awayLogo": "https://upload.wikimedia.org/wikipedia/en/1/1f/FC_Bayern_München_logo_%282017%29.svg",
      "time": "09:00 PM",
      "thumbnail": "https://picsum.photos/900/500?match4",
      "isLive": true,
      "streamTitle": "PSG vs Bayern",
      "streamUrl": "https://test-streams.mux.dev/x36xhzz/x36xhzz.m3u8"
    },
    {
      "id": 5,
      "leagueId": 4,
      "leagueName": "Serie A",
      "homeTeam": "Juventus",
      "awayTeam": "AC Milan",
      "homeLogo": "https://upload.wikimedia.org/wikipedia/commons/1/15/Juventus_FC_2017_logo.svg",
      "awayLogo": "https://upload.wikimedia.org/wikipedia/commons/d/d0/Logo_of_AC_Milan.svg",
      "time": "06:30 PM",
      "thumbnail": "https://picsum.photos/900/500?match5",
      "isLive": false,
      "streamTitle": "Juventus vs Milan",
      "streamUrl": "https://www.w3schools.com/html/movie.mp4"
    },
    {
      "id": 6,
      "leagueId": 1,
      "leagueName": "Premier League",
      "homeTeam": "Tottenham",
      "awayTeam": "Newcastle",
      "homeLogo": "https://upload.wikimedia.org/wikipedia/en/b/b4/Tottenham_Hotspur.svg",
      "awayLogo": "https://upload.wikimedia.org/wikipedia/en/5/56/Newcastle_United_Logo.svg",
      "time": "08:30 PM",
      "thumbnail": "https://picsum.photos/900/500?match6",
      "isLive": true,
      "streamTitle": "Tottenham vs Newcastle",
      "streamUrl": "https://test-streams.mux.dev/x36xhzz/x36xhzz.m3u8"
    }
  ]
}
